MoleculeACE/__init__.py
MoleculeACE/Data/__init__.py
MoleculeACE/Data/benchmark_data/CHEMBL1862_Ki.csv
MoleculeACE/Data/benchmark_data/CHEMBL1871_Ki.csv
MoleculeACE/Data/benchmark_data/CHEMBL2034_Ki.csv
MoleculeACE/Data/benchmark_data/CHEMBL2047_EC50.csv
MoleculeACE/Data/benchmark_data/CHEMBL204_Ki.csv
MoleculeACE/Data/benchmark_data/CHEMBL2147_Ki.csv
MoleculeACE/Data/benchmark_data/CHEMBL214_Ki.csv
MoleculeACE/Data/benchmark_data/CHEMBL218_EC50.csv
MoleculeACE/Data/benchmark_data/CHEMBL219_Ki.csv
MoleculeACE/Data/benchmark_data/CHEMBL228_Ki.csv
MoleculeACE/Data/benchmark_data/CHEMBL231_Ki.csv
MoleculeACE/Data/benchmark_data/CHEMBL233_Ki.csv
MoleculeACE/Data/benchmark_data/CHEMBL234_Ki.csv
MoleculeACE/Data/benchmark_data/CHEMBL235_EC50.csv
MoleculeACE/Data/benchmark_data/CHEMBL236_Ki.csv
MoleculeACE/Data/benchmark_data/CHEMBL237_EC50.csv
MoleculeACE/Data/benchmark_data/CHEMBL237_Ki.csv
MoleculeACE/Data/benchmark_data/CHEMBL238_Ki.csv
MoleculeACE/Data/benchmark_data/CHEMBL239_EC50.csv
MoleculeACE/Data/benchmark_data/CHEMBL244_Ki.csv
MoleculeACE/Data/benchmark_data/CHEMBL262_Ki.csv
MoleculeACE/Data/benchmark_data/CHEMBL264_Ki.csv
MoleculeACE/Data/benchmark_data/CHEMBL2835_Ki.csv
MoleculeACE/Data/benchmark_data/CHEMBL287_Ki.csv
MoleculeACE/Data/benchmark_data/CHEMBL2971_Ki.csv
MoleculeACE/Data/benchmark_data/CHEMBL3979_EC50.csv
MoleculeACE/Data/benchmark_data/CHEMBL4005_Ki.csv
MoleculeACE/Data/benchmark_data/CHEMBL4203_Ki.csv
MoleculeACE/Data/benchmark_data/CHEMBL4616_EC50.csv
MoleculeACE/Data/benchmark_data/CHEMBL4792_Ki.csv
MoleculeACE/Data/benchmark_data/__init__.py
MoleculeACE/Data/configures/__init__.py
MoleculeACE/Data/configures/benchmark/__init__.py
MoleculeACE/Data/configures/benchmark/CHEMBL1862_Ki/AFP_GRAPH.yml
MoleculeACE/Data/configures/benchmark/CHEMBL1862_Ki/CNN_SMILES.yml
MoleculeACE/Data/configures/benchmark/CHEMBL1862_Ki/GAT_GRAPH.yml
MoleculeACE/Data/configures/benchmark/CHEMBL1862_Ki/GBM_ECFP.yml
MoleculeACE-3.0.0.dist-info/LICENCE
MoleculeACE-3.0.0.dist-info/METADATA
MoleculeACE-3.0.0.dist-info/WHEEL
MoleculeACE-3.0.0.dist-info/top_level.txt
MoleculeACE-3.0.0.dist-info/RECORD
