Metadata-Version: 2.1
Name: MoleculeACE
Version: 3.0.0
Summary: MoleculeACE
Home-page: https://github.com/molML/MoleculeACE
Author: Derek van Tilborg
Author-email: d.w.v.tilborg@tue.nl
License: MIT
License-File: LICENCE
Requires-Dist: tqdm
Requires-Dist: requests
Requires-Dist: twine
Requires-Dist: importlib-metadata
Requires-Dist: pandas
Requires-Dist: numpy
Requires-Dist: chembl-webresource-client
Requires-Dist: scikit-learn
Requires-Dist: matplotlib
Requires-Dist: python-Levenshtein
Requires-Dist: rdkit-pypi
Requires-Dist: scikit-optimize
